<?xml version="1.0" encoding="UTF-8"?>
<MF0 version="1.1" packageUris="http://schema.mathworks.com/mf0/ci/19700101 http://schema.mathworks.com/mf0/sl_modelref_info/R2023a http://schema.mathworks.com/mf0/slexec_mm_sto/R2023a_202208151321 http://schema.mathworks.com/mf0/sltp_mm/R2023a_202209151115">
  <ModelRefInfoRepo.ModelRefInfoRoot type="ModelRefInfoRepo.ModelRefInfoRoot" uuid="3c4d863d-716c-451a-bb89-fc77d87619a1">
    <childModelRefInfo type="ModelRefInfoRepo.ChildModelRefInfo" uuid="6b95e66e-9442-41a1-8770-081db0a52889">
      <modelName>RpiFinalLEDShort</modelName>
      <modelPath>RpiFinalLEDShort</modelPath>
    </childModelRefInfo>
    <dataTransferInfos>AAFJTQAAAAAOAAAAOAAAAAYAAAAIAAAAAgAAAAAAAAAFAAAACAAAAAAAAAABAAAAAQAAAAAAAAAFAAQAAQAAAAEAAAAAAAAA</dataTransferInfos>
    <defaultsCMapping>{&quot;Inports&quot;:&quot;{\&quot;Name\&quot;:\&quot;Default\&quot;,\&quot;Checksum\&quot;:\&quot;Default\&quot;,\&quot;PerInstancePropertiesChecksum\&quot;:\&quot;\&quot;,\&quot;MemorySectionName\&quot;:\&quot;None\&quot;,\&quot;MemorySectionChecksum\&quot;:\&quot;None\&quot;}&quot;,&quot;Outports&quot;:&quot;{\&quot;Name\&quot;:\&quot;Default\&quot;,\&quot;Checksum\&quot;:\&quot;Default\&quot;,\&quot;PerInstancePropertiesChecksum\&quot;:\&quot;\&quot;,\&quot;MemorySectionName\&quot;:\&quot;None\&quot;,\&quot;MemorySectionChecksum\&quot;:\&quot;None\&quot;}&quot;,&quot;ParameterArguments&quot;:&quot;{\&quot;Name\&quot;:\&quot;Default\&quot;,\&quot;Checksum\&quot;:\&quot;Default\&quot;,\&quot;PerInstancePropertiesChecksum\&quot;:\&quot;\&quot;,\&quot;MemorySectionName\&quot;:\&quot;None\&quot;,\&quot;MemorySectionChecksum\&quot;:\&quot;None\&quot;}&quot;,&quot;LocalParameters&quot;:&quot;{\&quot;Name\&quot;:\&quot;Default\&quot;,\&quot;Checksum\&quot;:\&quot;Default\&quot;,\&quot;PerInstancePropertiesChecksum\&quot;:\&quot;\&quot;,\&quot;MemorySectionName\&quot;:\&quot;None\&quot;,\&quot;MemorySectionChecksum\&quot;:\&quot;None\&quot;}&quot;,&quot;GlobalParameters&quot;:&quot;{\&quot;Name\&quot;:\&quot;Default\&quot;,\&quot;Checksum\&quot;:\&quot;Default\&quot;,\&quot;PerInstancePropertiesChecksum\&quot;:\&quot;\&quot;,\&quot;MemorySectionName\&quot;:\&quot;None\&quot;,\&quot;MemorySectionChecksum\&quot;:\&quot;None\&quot;}&quot;,&quot;InternalData&quot;:&quot;{\&quot;Name\&quot;:\&quot;Default\&quot;,\&quot;Checksum\&quot;:\&quot;Default\&quot;,\&quot;PerInstancePropertiesChecksum\&quot;:\&quot;\&quot;,\&quot;MemorySectionName\&quot;:\&quot;None\&quot;,\&quot;MemorySectionChecksum\&quot;:\&quot;None\&quot;}&quot;,&quot;SharedLocalDataStores&quot;:&quot;{\&quot;Name\&quot;:\&quot;Default\&quot;,\&quot;Checksum\&quot;:\&quot;Default\&quot;,\&quot;PerInstancePropertiesChecksum\&quot;:\&quot;\&quot;,\&quot;MemorySectionName\&quot;:\&quot;None\&quot;,\&quot;MemorySectionChecksum\&quot;:\&quot;None\&quot;}&quot;,&quot;GlobalDataStores&quot;:&quot;{\&quot;Name\&quot;:\&quot;Default\&quot;,\&quot;Checksum\&quot;:\&quot;Default\&quot;,\&quot;PerInstancePropertiesChecksum\&quot;:\&quot;\&quot;,\&quot;MemorySectionName\&quot;:\&quot;None\&quot;,\&quot;MemorySectionChecksum\&quot;:\&quot;None\&quot;}&quot;,&quot;Constants&quot;:&quot;{\&quot;Name\&quot;:\&quot;Default\&quot;,\&quot;Checksum\&quot;:\&quot;Default\&quot;,\&quot;PerInstancePropertiesChecksum\&quot;:\&quot;\&quot;,\&quot;MemorySectionName\&quot;:\&quot;None\&quot;,\&quot;MemorySectionChecksum\&quot;:\&quot;None\&quot;}&quot;,&quot;DataTransfers&quot;:&quot;{\&quot;Name\&quot;:\&quot;Default\&quot;,\&quot;Checksum\&quot;:\&quot;Default\&quot;,\&quot;PerInstancePropertiesChecksum\&quot;:\&quot;\&quot;,\&quot;MemorySectionName\&quot;:\&quot;None\&quot;,\&quot;MemorySectionChecksum\&quot;:\&quot;None\&quot;}&quot;,&quot;ModelData&quot;:&quot;{\&quot;Name\&quot;:\&quot;Default\&quot;,\&quot;Checksum\&quot;:\&quot;Default\&quot;,\&quot;PerInstancePropertiesChecksum\&quot;:\&quot;\&quot;,\&quot;MemorySectionName\&quot;:\&quot;None\&quot;,\&quot;MemorySectionChecksum\&quot;:\&quot;None\&quot;}&quot;,&quot;InitializeTerminate&quot;:&quot;{\&quot;Name\&quot;:\&quot;Default\&quot;,\&quot;Checksum\&quot;:\&quot;Default\&quot;,\&quot;PerInstancePropertiesChecksum\&quot;:\&quot;\&quot;,\&quot;MemorySectionName\&quot;:\&quot;None\&quot;,\&quot;MemorySectionChecksum\&quot;:\&quot;None\&quot;}&quot;,&quot;Execution&quot;:&quot;{\&quot;Name\&quot;:\&quot;Default\&quot;,\&quot;Checksum\&quot;:\&quot;Default\&quot;,\&quot;PerInstancePropertiesChecksum\&quot;:\&quot;\&quot;,\&quot;MemorySectionName\&quot;:\&quot;None\&quot;,\&quot;MemorySectionChecksum\&quot;:\&quot;None\&quot;}&quot;,&quot;SharedUtility&quot;:&quot;{\&quot;Name\&quot;:\&quot;Default\&quot;,\&quot;Checksum\&quot;:\&quot;Default\&quot;,\&quot;PerInstancePropertiesChecksum\&quot;:\&quot;\&quot;,\&quot;MemorySectionName\&quot;:\&quot;None\&quot;,\&quot;MemorySectionChecksum\&quot;:\&quot;None\&quot;}&quot;}</defaultsCMapping>
    <fastestNoncontSigFeedingDerivPorts>-1.0</fastestNoncontSigFeedingDerivPorts>
    <fundamentalSampleTimePeriod>1.0</fundamentalSampleTimePeriod>
    <hasBlockWithPeriodicDiscreteSampleTime>true</hasBlockWithPeriodicDiscreteSampleTime>
    <hasBwsAccessed>true</hasBwsAccessed>
    <hasBwsAccessedByAnyModel>true</hasBwsAccessedByAnyModel>
    <hasNonVirtualConstantTs>true</hasNonVirtualConstantTs>
    <isBdInSimModeForSimCodegenVariants>false</isBdInSimModeForSimCodegenVariants>
    <isInlineParamsOn>true</isInlineParamsOn>
    <loggingSaveFormat>4</loggingSaveFormat>
    <maxFreqHz>-1.0</maxFreqHz>
    <numDStateRecs>1</numDStateRecs>
    <numDataInputPorts>0</numDataInputPorts>
    <numLoggableDStateRecs>1</numLoggableDStateRecs>
    <numLoggableJacobianDStates>1</numLoggableJacobianDStates>
    <runtimeNonFcnCallRateInfos type="ModelRefInfoRepo.RateInfo">
      <compiled>true</compiled>
      <nonFcnCallPartitionName>D1</nonFcnCallPartitionName>
      <period>1.0</period>
      <priority>40</priority>
      <rateIdx>0</rateIdx>
    </runtimeNonFcnCallRateInfos>
    <sampleTimeInheritanceRule>2</sampleTimeInheritanceRule>
    <solverStatusFlags>331</solverStatusFlags>
    <timingAndTaskingRegistry>&lt;?xml version=&quot;1.0&quot;?&gt;
&lt;slexec_sto version=&quot;1.1&quot; packageUris=&quot;http://schema.mathworks.com/mf0/slexec_mm_sto/R2023a_202208151321&quot;&gt;
  &lt;sto.Registry type=&quot;sto.Registry&quot; uuid=&quot;4a6657c6-60b5-4f9d-8726-7a15db2c5fc6&quot;&gt;
    &lt;executionSpec&gt;Undetermined&lt;/executionSpec&gt;
    &lt;identifier&gt;RpiFinalLEDShort&lt;/identifier&gt;
    &lt;clockRegistry type=&quot;sto.ClockRegistry&quot; uuid=&quot;136dc08b-ead3-49da-8d17-3c3ac6e95f60&quot;&gt;
      &lt;clocks type=&quot;sto.Timer&quot; uuid=&quot;2df51f36-4005-4278-a477-84ac31b5e468&quot;&gt;
        &lt;clockTickConstraint&gt;PeriodicWithFixedResolution&lt;/clockTickConstraint&gt;
        &lt;computedFundamentalDiscretePeriod&gt;1.0&lt;/computedFundamentalDiscretePeriod&gt;
        &lt;fastestDiscreteRate type=&quot;sto.ClassicPeriodicDiscreteRate&quot; uuid=&quot;48b2a66c-2964-47d2-a9b6-e919ad588bab&quot;/&gt;
        &lt;isDefaultTimer&gt;true&lt;/isDefaultTimer&gt;
        &lt;resolution&gt;1.0&lt;/resolution&gt;
        &lt;timeAdvanceMode&gt;FixedStep&lt;/timeAdvanceMode&gt;
        &lt;identifier&gt;RpiFinalLEDShort::defaultTimer&lt;/identifier&gt;
        &lt;rates type=&quot;sto.ClassicPeriodicDiscreteRate&quot; uuid=&quot;48b2a66c-2964-47d2-a9b6-e919ad588bab&quot;&gt;
          &lt;annotation&gt;D1&lt;/annotation&gt;
          &lt;clockId&gt;RpiFinalLEDShort::defaultTimer&lt;/clockId&gt;
          &lt;colorIndex&gt;2&lt;/colorIndex&gt;
          &lt;description&gt;Discrete 1&lt;/description&gt;
          &lt;taskId&gt;_task0&lt;/taskId&gt;
          &lt;rateSpec type=&quot;sto.RateSpec&quot; uuid=&quot;f531e44b-e384-4692-9990-56319f6d2a5b&quot;&gt;
            &lt;period&gt;1.0&lt;/period&gt;
            &lt;rateType&gt;ClassicPeriodicDiscrete&lt;/rateType&gt;
          &lt;/rateSpec&gt;
        &lt;/rates&gt;
        &lt;baseRate type=&quot;sto.ClassicPeriodicDiscreteRate&quot; uuid=&quot;6b99fb8f-dc2e-47e4-97aa-831e18095675&quot;&gt;
          &lt;annotation&gt;D1&lt;/annotation&gt;
          &lt;clockId&gt;RpiFinalLEDShort::defaultTimer&lt;/clockId&gt;
          &lt;colorIndex&gt;2&lt;/colorIndex&gt;
          &lt;description&gt;Discrete 1&lt;/description&gt;
          &lt;taskId&gt;_task0&lt;/taskId&gt;
          &lt;rateSpec type=&quot;sto.RateSpec&quot; uuid=&quot;156ba300-6124-4875-9a49-c8dafcfb330f&quot;&gt;
            &lt;period&gt;1.0&lt;/period&gt;
            &lt;rateType&gt;ClassicPeriodicDiscrete&lt;/rateType&gt;
          &lt;/rateSpec&gt;
        &lt;/baseRate&gt;
      &lt;/clocks&gt;
      &lt;clocks type=&quot;sto.Event&quot; uuid=&quot;0f3ef503-f903-46ea-b301-56df3c5a0f9e&quot;&gt;
        &lt;eventType&gt;PARAMETER_CHANGE_EVENT&lt;/eventType&gt;
        &lt;cNum&gt;1&lt;/cNum&gt;
        &lt;clockType&gt;Event&lt;/clockType&gt;
        &lt;identifier&gt;ParameterChangeEvent&lt;/identifier&gt;
        &lt;rates type=&quot;sto.ModelWideEventRate&quot; uuid=&quot;d861b5d1-15d2-47ef-b028-641b0bd5bda0&quot;&gt;
          &lt;clockId&gt;ParameterChangeEvent&lt;/clockId&gt;
          &lt;rateIdx&gt;-1&lt;/rateIdx&gt;
          &lt;taskId&gt;ModelWideParameterChangeEvent&lt;/taskId&gt;
          &lt;useForExecution&gt;NotForExecution&lt;/useForExecution&gt;
          &lt;rateSpec type=&quot;sto.RateSpec&quot; uuid=&quot;d6acc89a-0dad-406e-a4fd-f6a024858a30&quot;&gt;
            &lt;period&gt;inf&lt;/period&gt;
            &lt;rateType&gt;ModelWideParameterChangeEvent&lt;/rateType&gt;
          &lt;/rateSpec&gt;
        &lt;/rates&gt;
      &lt;/clocks&gt;
      &lt;timeAdvanceMode&gt;FixedStep&lt;/timeAdvanceMode&gt;
    &lt;/clockRegistry&gt;
    &lt;taskRegistry type=&quot;sto.TaskRegistry&quot; uuid=&quot;0098334e-9fbb-4038-b2d9-053df3a5d050&quot;&gt;
      &lt;rootTaskHierarchyElements type=&quot;sto.Task&quot; uuid=&quot;abeb25fa-7105-461f-afb3-c66210628499&quot;&gt;
        &lt;isExplicit&gt;true&lt;/isExplicit&gt;
        &lt;rates type=&quot;sto.ModelWideEventRate&quot; uuid=&quot;5bdf06b6-eaee-4e62-a5a0-7a02eddc2337&quot;&gt;
          &lt;clockId&gt;ParameterChangeEvent&lt;/clockId&gt;
          &lt;rateIdx&gt;-1&lt;/rateIdx&gt;
          &lt;taskId&gt;ModelWideParameterChangeEvent&lt;/taskId&gt;
          &lt;useForExecution&gt;NotForExecution&lt;/useForExecution&gt;
          &lt;rateSpec type=&quot;sto.RateSpec&quot; uuid=&quot;c85c2af0-64d4-40e8-b7bf-79bfe8c138f2&quot;&gt;
            &lt;period&gt;inf&lt;/period&gt;
            &lt;rateType&gt;ModelWideParameterChangeEvent&lt;/rateType&gt;
          &lt;/rateSpec&gt;
        &lt;/rates&gt;
        &lt;schedulingClockId&gt;ParameterChangeEvent&lt;/schedulingClockId&gt;
        &lt;timeKeeperClockId&gt;RpiFinalLEDShort::defaultTimer&lt;/timeKeeperClockId&gt;
        &lt;elementType&gt;Task&lt;/elementType&gt;
        &lt;identifier&gt;ModelWideParameterChangeEvent&lt;/identifier&gt;
        &lt;priority&gt;-1&lt;/priority&gt;
      &lt;/rootTaskHierarchyElements&gt;
      &lt;rootTaskHierarchyElements type=&quot;sto.Task&quot; uuid=&quot;91203905-2397-450a-babb-d578b502d411&quot;&gt;
        &lt;isExecutable&gt;true&lt;/isExecutable&gt;
        &lt;orderIndex&gt;1&lt;/orderIndex&gt;
        &lt;rates type=&quot;sto.ClassicPeriodicDiscreteRate&quot; uuid=&quot;2f94b391-96c6-4e22-a94b-219f001c30af&quot;&gt;
          &lt;annotation&gt;D1&lt;/annotation&gt;
          &lt;clockId&gt;RpiFinalLEDShort::defaultTimer&lt;/clockId&gt;
          &lt;colorIndex&gt;2&lt;/colorIndex&gt;
          &lt;description&gt;Discrete 1&lt;/description&gt;
          &lt;taskId&gt;_task0&lt;/taskId&gt;
          &lt;rateSpec type=&quot;sto.RateSpec&quot; uuid=&quot;912211f2-a7c7-411a-b93a-23e23e85364d&quot;&gt;
            &lt;period&gt;1.0&lt;/period&gt;
            &lt;rateType&gt;ClassicPeriodicDiscrete&lt;/rateType&gt;
          &lt;/rateSpec&gt;
        &lt;/rates&gt;
        &lt;schedulingClockId&gt;RpiFinalLEDShort::defaultTimer&lt;/schedulingClockId&gt;
        &lt;timeKeeperClockId&gt;RpiFinalLEDShort::defaultTimer&lt;/timeKeeperClockId&gt;
        &lt;elementType&gt;Task&lt;/elementType&gt;
        &lt;identifier&gt;_task0&lt;/identifier&gt;
        &lt;priority&gt;40&lt;/priority&gt;
      &lt;/rootTaskHierarchyElements&gt;
      &lt;taskDependencyGraph type=&quot;sto.SerializedTaskConnectionList&quot; uuid=&quot;e5e5eddd-0451-4be9-bccb-f2c513036ee5&quot;&gt;
        &lt;clockIdentifier&gt;RpiFinalLEDShort::defaultTimer&lt;/clockIdentifier&gt;
        &lt;taskIdentifier&gt;_task0&lt;/taskIdentifier&gt;
      &lt;/taskDependencyGraph&gt;
      &lt;taskDependencyGraph type=&quot;sto.SerializedTaskConnectionList&quot; uuid=&quot;1201e618-b324-4456-a602-5d1e8c6ac5be&quot;&gt;
        &lt;clockIdentifier&gt;ParameterChangeEvent&lt;/clockIdentifier&gt;
        &lt;taskIdentifier&gt;ModelWideParameterChangeEvent&lt;/taskIdentifier&gt;
      &lt;/taskDependencyGraph&gt;
      &lt;taskingMode&gt;ClassicMultiTasking&lt;/taskingMode&gt;
    &lt;/taskRegistry&gt;
  &lt;/sto.Registry&gt;
&lt;/slexec_sto&gt;</timingAndTaskingRegistry>
    <FMUBlockMap type="ModelRefInfoRepo.FMUBlockInfo" uuid="7df6c7c9-775a-4689-beef-5a49ebffd181"/>
    <codeGenInfo type="ModelRefInfoRepo.CodeGenInformation" uuid="d0a42b3d-45fd-4082-a461-7f120db32f94"/>
    <compiledVariantInfos type="ModelRefInfoRepo.CompiledVariantInfoMap" uuid="9181b35d-1a12-4ef9-a3f5-76aeafa9dc2c"/>
    <configSettingsForConsistencyChecks type="ModelRefInfoRepo.ConfigSettingsForConsistencyChecks" uuid="235224e7-da3e-4791-9c27-453d231f50b4">
      <fixedStepSize>1.0</fixedStepSize>
      <frameDiagnosticSetting>2</frameDiagnosticSetting>
      <hasHybridSampleTime>true</hasHybridSampleTime>
      <signalLoggingSaveFormat>2</signalLoggingSaveFormat>
      <simSIMDOptimization>1</simSIMDOptimization>
      <solverName>FixedStepDiscrete</solverName>
      <solverType>SOLVER_TYPE_FIXEDSTEP</solverType>
      <hardwareSettings type="ModelRefInfoRepo.HardwareSettings" uuid="16bd3a3e-9cbc-400d-940d-caa68141919d">
        <prodBitPerChar>8</prodBitPerChar>
        <prodBitPerDouble>64</prodBitPerDouble>
        <prodBitPerFloat>32</prodBitPerFloat>
        <prodBitPerInt>32</prodBitPerInt>
        <prodBitPerLong>32</prodBitPerLong>
        <prodBitPerLongLong>64</prodBitPerLongLong>
        <prodBitPerPointer>32</prodBitPerPointer>
        <prodBitPerPtrDiffT>32</prodBitPerPtrDiffT>
        <prodBitPerShort>16</prodBitPerShort>
        <prodBitPerSizeT>32</prodBitPerSizeT>
        <prodEndianess>1</prodEndianess>
        <prodLargestAtomicFloat>1</prodLargestAtomicFloat>
        <prodLargestAtomicInteger>3</prodLargestAtomicInteger>
        <prodShiftRight>true</prodShiftRight>
        <prodWordSize>32</prodWordSize>
      </hardwareSettings>
    </configSettingsForConsistencyChecks>
    <controllableInputRatesMap type="ModelRefInfoRepo.VarTsUIDMap" uuid="c841a33c-64e9-4925-b278-809b6f02e887"/>
    <controllableOutputRatesMap type="ModelRefInfoRepo.VarTsUIDMap" uuid="315bd8c3-4fba-4c24-95f4-43c250f507d8"/>
    <dataPortGroup type="ModelRefInfoRepo.DataPortGroup" uuid="eb0c06e9-d123-4623-a0b2-0bf30e63c14f"/>
    <expFcnUnconnectedDataPortGroup type="ModelRefInfoRepo.DataPortGroup" uuid="49b17648-df78-41df-ae67-ad1c3b02fee2"/>
    <interfaceParameterInfo type="ModelRefInfoRepo.InterfaceParameterInfo" uuid="0a8e80e1-7da8-4266-83ef-afa4a2dbab55"/>
    <messageInfo type="ModelRefInfoRepo.MessageInformation" uuid="566c8706-e7af-485a-9be1-4ce40bf4e1d1"/>
    <methodInfo type="ModelRefInfoRepo.MethodExistenceInfo" uuid="9e95284d-f56f-4d37-b83b-30a5031a9374">
      <hasSystemInitializeMethod>true</hasSystemInitializeMethod>
      <hasSystemResetMethod>true</hasSystemResetMethod>
      <hasTerminateMethod>true</hasTerminateMethod>
      <hasUpdateMethod>true</hasUpdateMethod>
    </methodInfo>
    <periodicEventPortUnsupportedBlockInfo type="ModelRefInfoRepo.PeriodicEventPortUnsupportedBlockInfo" uuid="aab14cc4-d24d-4aff-bf0e-fe79cc71bc1b"/>
    <portGroupsRequireSameRate type="ModelRefInfoRepo.PortGroupsRequireSameRate" uuid="02c2e086-928a-406a-a52c-a9ce86b16c9e">
      <DSMPortGroups type="ModelRefInfoRepo.NameToPortGroupIdxVectMap" uuid="a3f5e100-d4f2-46af-978a-adef404911f8"/>
      <GlobalDSMPortGroups type="ModelRefInfoRepo.NameToPortGroupIdxVectMap" uuid="55b51e86-9f39-4720-a2c3-c44282fd475b"/>
      <mergedPortGroups type="ModelRefInfoRepo.NameToPortGroupIdxVectMap" uuid="0738802a-87e6-48a1-9526-b53d9fc6c43f"/>
    </portGroupsRequireSameRate>
    <rateBasedMdlGlobalDSMRateSpec type="ModelRefInfoRepo.GlobalDSMRateSpecMap" uuid="897d461f-3ec5-44f2-a22a-856b376e396a"/>
    <rateSpecOfGlobalDSMAccessedByDescExpFcnMdlMap type="ModelRefInfoRepo.GlobalDSMRateSpecMap" uuid="791b4a2e-9f43-4515-8f34-ee07a24ad658"/>
    <rootBlockDiagramInterface type="ci.Model" uuid="a80a9b7e-3089-43b5-8fa6-1d14b7633d69">
      <p_RootComponentInterface type="ci.ComponentInterface" uuid="32076cb9-38d5-479b-9d99-020336bb20f3">
        <p_Name>RpiFinalLEDShort</p_Name>
        <p_Type>ROOT</p_Type>
      </p_RootComponentInterface>
    </rootBlockDiagramInterface>
    <simulinkFunctions type="ModelRefInfoRepo.SimulinkFunctions" uuid="17c57bec-9f1f-43ad-bb59-80b9a401ea93">
      <compSimulinkFunctionCatalog></compSimulinkFunctionCatalog>
    </simulinkFunctions>
    <sltpContext type="sltp.mm.core.Context" uuid="7879dfae-9c3e-498b-9cea-10d67b0075bc">
      <unusedTaskIds>1</unusedTaskIds>
      <unusedTaskIds>2</unusedTaskIds>
      <unusedTaskIds>3</unusedTaskIds>
      <unusedTaskIds>4</unusedTaskIds>
      <defaultEventBehavior type="sltp.mm.core.EventBehavior" uuid="3e917462-e6f8-4ab0-8a35-d3f2be7535ad"/>
      <editorState type="sltp.mm.core.EditorState" uuid="b8f5e13f-db8a-46c3-bcdd-db70d65b2763">
        <isSynchronized>true</isSynchronized>
        <panelState type="sltp.mm.core.EditorPanelState" uuid="585e18ca-b0f7-4d6b-9ce8-35402d41b752"/>
      </editorState>
      <rootTask type="sltp.mm.core.Task" uuid="5756a0f6-5c09-4c44-a387-53fd5d8c143e">
        <context type="sltp.mm.core.Context" uuid="7879dfae-9c3e-498b-9cea-10d67b0075bc"/>
        <explicit>false</explicit>
        <name>Default</name>
        <priority>-2147483648</priority>
        <subgraph type="sltp.mm.core.Graph" uuid="1d506656-078c-4d0e-b7bf-d8448fd952b8">
          <tasks type="sltp.mm.core.Task" uuid="09c99c96-3538-4e99-9cb4-6c718a97503f">
            <context type="sltp.mm.core.Context" uuid="7879dfae-9c3e-498b-9cea-10d67b0075bc"/>
            <explicit>false</explicit>
            <id>5</id>
            <isTimed>true</isTimed>
            <name>D1</name>
            <priority>40</priority>
            <rates type="sltp.mm.core.Rate" uuid="963a6c9f-cc32-4454-8c07-6109c2f8380e">
              <annotation>D1</annotation>
              <color>-436207361</color>
              <hasBlocks>true</hasBlocks>
              <identifier>ClassicPeriodicDiscrete10</identifier>
              <rateIndex>0</rateIndex>
              <rateSpec type="sltp.mm.core.RateSpec">
                <period>1.0</period>
              </rateSpec>
              <sti>0</sti>
            </rates>
          </tasks>
        </subgraph>
      </rootTask>
    </sltpContext>
    <stateWriterToOwnerMap type="ModelRefInfoRepo.StateWriterInfo" uuid="4a9be728-d4eb-4733-93e4-e6936d248b47"/>
    <stoClientDataRegistry type="sto.ClientDataRegistry" uuid="5e70a445-f2fd-4453-a793-bba1b95b3ba1">
      <dataSets type="sto.ClientClockNamedDataSet" uuid="2f4816cc-72d4-46b1-97f3-690145d2d09a">
        <tag>sltpEvents</tag>
      </dataSets>
      <dataSets type="sto.ClientTaskHierarchyElementNamedDataSet" uuid="b865e267-74e9-4269-82fc-796cf4a9c9b4">
        <tag>sltpTaskGroups</tag>
      </dataSets>
      <dataSets type="sto.ClientTaskHierarchyElementNamedDataSet" uuid="7332dc50-2dee-4328-a79b-234afccfc768">
        <dSet type="ModelRefInfoRepo.SltpTaskData" uuid="64f351ab-ceee-4096-a2e3-cbd9549e7e68"/>
        <tSet type="ModelRefInfoRepo.SltpTaskData" uuid="64f351ab-ceee-4096-a2e3-cbd9549e7e68">
          <dataName>D1</dataName>
          <linkedSet type="sto.ClientTaskHierarchyElementNamedDataSet" uuid="7332dc50-2dee-4328-a79b-234afccfc768"/>
          <id type="sto.TaskHierarchyElementId">
            <clockId>RpiFinalLEDShort::defaultTimer</clockId>
            <id>_task0</id>
          </id>
        </tSet>
        <tag>sltpTasks</tag>
      </dataSets>
    </stoClientDataRegistry>
    <varTsUIDMap type="ModelRefInfoRepo.VarTsUIDMap" uuid="475fa732-bfb7-4d37-b38b-1fc5831854da"/>
  </ModelRefInfoRepo.ModelRefInfoRoot>
</MF0>